jsonapp/__init__.py
jsonapp/jsonapp_cli.py
jsonapp/core/__init__.py
jsonapp/core/jsonapp_main.py
jsonapp/utils/__init__.py
jsonapp/utils/cli_util.py
jsonapp/utils/dict_util.py
jsonapp/utils/input_util.py
jsonapp/utils/json_util.py
jsonapp/utils/print_util.py
jsonapp/utils/result_util.py
jsonapp/utils/string_base_util.py
jsonapp/utils/string_util.py
jsonapp_package-0.1.2.dist-info/DESCRIPTION.rst
jsonapp_package-0.1.2.dist-info/METADATA
jsonapp_package-0.1.2.dist-info/RECORD
jsonapp_package-0.1.2.dist-info/WHEEL
jsonapp_package-0.1.2.dist-info/entry_points.txt
jsonapp_package-0.1.2.dist-info/metadata.json
jsonapp_package-0.1.2.dist-info/top_level.txt
