Metadata-Version: 2.0
Name: jsonapp-package
Version: 0.1.2
Summary: A command line utility that helps dealing with JSON data.
Home-page: https://github.com/eyalev/jsonapp
Author: Eyal Levin
Author-email: eyalev@gmail.com
License: MIT license
Keywords: jsonapp
Platform: UNKNOWN
Classifier: Development Status :: 2 - Pre-Alpha
Classifier: Intended Audience :: Developers
Classifier: License :: OSI Approved :: MIT License
Classifier: Natural Language :: English
Classifier: Programming Language :: Python :: 2
Classifier: Programming Language :: Python :: 2.6
Classifier: Programming Language :: Python :: 2.7
Classifier: Programming Language :: Python :: 3
Classifier: Programming Language :: Python :: 3.3
Classifier: Programming Language :: Python :: 3.4
Classifier: Programming Language :: Python :: 3.5
Requires-Dist: Click (>=6.0)
Requires-Dist: six (==1.10.0)
Requires-Dist: xerox (==0.4.1)
